cosmoabc/ABC_functions.py
cosmoabc/ABC_sampler.py
cosmoabc/__init__.py
cosmoabc/distances.py
cosmoabc/plots.py
cosmoabc/priors.py
cosmoabc/sim_NumCosmo_cluster.py
cosmoabc/weighted_gaussian_kde.py
cosmoabc/bin/continue_ABC.py
cosmoabc/bin/continue_ABC_NumCosmo.py
cosmoabc/bin/plot_ABC.py
cosmoabc/bin/run_ABC.py
cosmoabc/bin/run_ABC_NumCosmo.py
cosmoabc/data/SPT.dat
cosmoabc/examples/data_format_SZ.dat
cosmoabc/examples/input_NumCosmo.txt
cosmoabc/examples/toy_model.input
cosmoabc/tests/test_ABC_algorithm.py
cosmoabc/tests/test_ABC_distance.py
cosmoabc-1.0.10.data/scripts/continue_ABC.py
cosmoabc-1.0.10.data/scripts/continue_ABC_NumCosmo.py
cosmoabc-1.0.10.data/scripts/plot_ABC.py
cosmoabc-1.0.10.data/scripts/run_ABC.py
cosmoabc-1.0.10.data/scripts/run_ABC_NumCosmo.py
cosmoabc-1.0.10.data/scripts/test_ABC_algorithm.py
cosmoabc-1.0.10.data/scripts/test_ABC_distance.py
cosmoabc-1.0.10.dist-info/LICENCE
cosmoabc-1.0.10.dist-info/METADATA
cosmoabc-1.0.10.dist-info/WHEEL
cosmoabc-1.0.10.dist-info/top_level.txt
cosmoabc-1.0.10.dist-info/RECORD
