Metadata-Version: 2.1
Name: cosmoabc
Version: 1.0.10
Summary: Python ABC sampler
Home-page: https://github.com/COINtoolbox/cosmoabc
Author: E. E. O. Ishida, S. D. P. Vitenti, M. Penna-Lima,J. Cisewski, R. S. de Souza, A. M. M. Trindade, V. C. Busti, E. Cameron
Author-email: emille@cosmostatistics-initiative.org
License: GNU Public License
Platform: UNKNOWN
Classifier: Programming Language :: Python
Classifier: Natural Language :: English
Classifier: Environment :: X11 Applications
Classifier: Intended Audience :: Science/Research
Classifier: License :: OSI Approved :: GNU General Public License (GPL)
Classifier: Topic :: Software Development :: Libraries :: Python Modules
Classifier: Topic :: Scientific/Engineering :: Astronomy
Requires-Dist: numpy (>=1.8.2)
Requires-Dist: scipy (>=1.7.0)
Requires-Dist: statsmodels (>=0.12.2)
Requires-Dist: matplotlib (>=3.4.2)
Requires-Dist: distribute
Requires-Dist: datetime
